trycast/__init__.py
trycast/py.typed
trycast-1.2.1.dist-info/LICENSE.md
trycast-1.2.1.dist-info/METADATA
trycast-1.2.1.dist-info/WHEEL
trycast-1.2.1.dist-info/RECORD
