Metadata-Version: 2.3
Name: trycast
Version: 1.2.1
Summary: 
License: MIT
Author: David Foster
Author-email: david@dafoster.net
Requires-Python: >=3.8.1
Classifier: Development Status :: 5 - Production/Stable
Classifier: Environment :: Console
Classifier: Intended Audience :: Developers
Classifier: License :: OSI Approved :: MIT License
Classifier: Operating System :: OS Independent
Classifier: Programming Language :: Python :: 3
Classifier: Programming Language :: Python :: 3.9
Classifier: Programming Language :: Python :: 3.10
Classifier: Programming Language :: Python :: 3.11
Classifier: Programming Language :: Python :: 3.12
Classifier: Programming Language :: Python :: 3.13
Classifier: Programming Language :: Python :: 3.8
Classifier: Topic :: Software Development
Classifier: Typing :: Typed
Project-URL: Documentation, https://dafoster.net/projects/trycast/
Project-URL: Homepage, https://dafoster.net/projects/trycast/
Project-URL: Repository, https://github.com/davidfstr/trycast
Project-URL: Release notes, https://github.com/davidfstr/trycast#changelog
